pyVHR/__init__.py
pyVHR/BPM/BPM.py
pyVHR/BPM/__init__.py
pyVHR/BPM/utils.py
pyVHR/BVP/BVP.py
pyVHR/BVP/__init__.py
pyVHR/BVP/filters.py
pyVHR/BVP/methods.py
pyVHR/BVP/utils.py
pyVHR/analysis/__init__.py
pyVHR/analysis/multi_method_suite.py
pyVHR/analysis/pipeline.py
pyVHR/analysis/stats.py
pyVHR/datasets/__init__.py
pyVHR/datasets/cohface.py
pyVHR/datasets/dataset.py
pyVHR/datasets/lgi_ppgi.py
pyVHR/datasets/mahnob.py
pyVHR/datasets/pure.py
pyVHR/datasets/sample.py
pyVHR/datasets/ubfc1.py
pyVHR/datasets/ubfc2.py
pyVHR/extraction/__init__.py
pyVHR/extraction/sig_extraction_methods.py
pyVHR/extraction/sig_processing.py
pyVHR/extraction/skin_extraction_methods.py
pyVHR/extraction/utils.py
pyVHR/plot/__init__.py
pyVHR/plot/visualize.py
pyVHR/realtime/GUI.py
pyVHR/realtime/VHRroutine.py
pyVHR/realtime/__init__.py
pyVHR/realtime/params.py
pyVHR/realtime/video_capture.py
pyVHR/resources/__init__.py
pyVHR/resources/faceparsing/__init__.py
pyVHR/resources/faceparsing/evaluate.py
pyVHR/resources/faceparsing/face_dataset.py
pyVHR/resources/faceparsing/logger.py
pyVHR/resources/faceparsing/loss.py
pyVHR/resources/faceparsing/makeup.py
pyVHR/resources/faceparsing/model.py
pyVHR/resources/faceparsing/optimizer.py
pyVHR/resources/faceparsing/prepropess_data.py
pyVHR/resources/faceparsing/resnet.py
pyVHR/resources/faceparsing/test.py
pyVHR/resources/faceparsing/train.py
pyVHR/resources/faceparsing/transform.py
pyVHR/resources/faceparsing/modules/__init__.py
pyVHR/resources/faceparsing/modules/bn.py
pyVHR/resources/faceparsing/modules/deeplab.py
pyVHR/resources/faceparsing/modules/dense.py
pyVHR/resources/faceparsing/modules/functions.py
pyVHR/resources/faceparsing/modules/misc.py
pyVHR/resources/faceparsing/modules/residual.py
pyVHR/resources/img/__init__.py
pyVHR/utils/__init__.py
pyVHR/utils/cuda_utils.py
pyVHR/utils/ecg.py
pyVHR/utils/elapse.py
pyVHR/utils/errors.py
pyVHR/utils/printutils.py
pyVHR-1.0.2.dist-info/LICENSE
pyVHR-1.0.2.dist-info/METADATA
pyVHR-1.0.2.dist-info/WHEEL
pyVHR-1.0.2.dist-info/top_level.txt
pyVHR-1.0.2.dist-info/RECORD
