Metadata-Version: 2.1
Name: pyVHR
Version: 1.0.2
Summary: Package for rPPG methods
Home-page: https://github.com/phuselab/pyVHR
Author: Vittorio Cuculo <vittorio.cuculo@unimi.it>, Donatello Conte <donatello.conte@univ-tours.fr>, Alessandro D'Amelio <alessandro.damelio@unimi.it>, Giuliano Grossi <giuliano.grossi@unimi.it>, Edoardo Mortara <edoardo.mortara@studenti.unimi.it>
Author-email: 
License: UNKNOWN
Platform: UNKNOWN
Classifier: Programming Language :: Python :: 3
Classifier: License :: OSI Approved :: BSD License
Classifier: Operating System :: OS Independent
Requires-Python: >=3.6
License-File: LICENSE
